framed_title.py
framed_title-0.0.3.dist-info/LICENSE
framed_title-0.0.3.dist-info/METADATA
framed_title-0.0.3.dist-info/WHEEL
framed_title-0.0.3.dist-info/top_level.txt
framed_title-0.0.3.dist-info/RECORD
