Metadata-Version: 2.1
Name: framed-title
Version: 0.0.3
Summary: Prints a framed title
Home-page: https://github.com/xelorabb/framed_title
Author: xelorabb
Author-email: xelorabb@gmail.com
License: MIT
Keywords: python,text,frame,title,terminal,console
Platform: UNKNOWN
Classifier: Intended Audience :: Developers
Classifier: Programming Language :: Python :: 3.9
Classifier: Operating System :: OS Independent
License-File: LICENSE
Requires-Dist: yatts (>=1.0.0)
